{
  "experiment_id": "exp-20260428-020",
  "status": "observed_only",
  "lane": "universe_scout",
  "owner": "universe_scout",
  "hypothesis": "A narrow shadow universe can surface replayable low-overlap candidates with useful forward returns without adding production tickers.",
  "change_type": "universe_expansion",
  "single_causal_variable": "narrow shadow universe definition",
  "baseline_result_file": "data/backtest_results_20260427.json",
  "allowed_write_scope": [
    "quant/experiments/exp_20260428_020_narrow_shadow_universe_definition.py",
    "data/experiments/exp-20260428-020/exp_20260428_020_narrow_shadow_universe_definition.json",
    "docs/experiments/tickets/exp-20260428-020.json",
    "docs/experiments/logs/exp-20260428-020.json",
    "docs/experiment_log.jsonl",
    "docs/experiment_registry.json"
  ],
  "must_not_touch": [
    "quant/constants.py",
    "quant/signal_engine.py",
    "quant/risk_engine.py",
    "quant/portfolio_engine.py"
  ],
  "locked_variables": [
    "narrow shadow universe definition"
  ],
  "evaluation_windows": [
    {
      "start": "2025-10-23",
      "end": "2026-04-21"
    },
    {
      "start": "2025-04-23",
      "end": "2025-10-22"
    },
    {
      "start": "2024-10-02",
      "end": "2025-04-22"
    }
  ],
  "acceptance_rule": "shadow universe only; observed_only unless non-overlap and forward quality justify promotion",
  "created_at": "2026-04-28T06:25:23+00:00",
  "claimed_at": "2026-04-28T06:25:31+00:00",
  "completed_at": "2026-04-28T06:28:52+00:00",
  "result": {
    "decision": "observed_only",
    "acceptance_reasons": [],
    "before_result_file": "data/backtest_results_20260427.json",
    "after_result_file": "data/backtest_results_20260427.json",
    "delta_metrics": {
      "expected_value_score": 0.0,
      "sharpe": 0.0,
      "sharpe_daily": 0.0,
      "total_return_pct": 0.0,
      "max_drawdown_pct": 0.0,
      "win_rate": 0.0,
      "trade_count": 0,
      "survival_rate": 0.0,
      "total_pnl": 0.0
    }
  }
}
