{
  "generated_at": "2026-02-17T19:33:30.072387",
  "asof_date": "2026-02-17",
  "universe": [
    "AMD",
    "APP",
    "COIN",
    "CRDO",
    "GOOG",
    "IAU",
    "MCD",
    "META",
    "MU",
    "NFLX",
    "NVDA",
    "QQQ",
    "TSLA"
  ],
  "window": 20,
  "signals": {
    "AMD": {
      "close": 203.08,
      "20d_high": 266.96,
      "20d_low": 190.72,
      "breakout": false,
      "breakdown": false,
      "position": {
        "shares": 7,
        "avg_cost": 27.59,
        "unrealized_pnl_pct": 6.3593,
        "distance_to_hard_stop_pct": 0.8804,
        "hard_stop_price": 24.28
      }
    },
    "APP": {
      "close": 376.38,
      "20d_high": 615.27,
      "20d_low": 359.0,
      "breakout": false,
      "breakdown": false,
      "position": {
        "shares": 4,
        "avg_cost": 600,
        "unrealized_pnl_pct": -0.3727,
        "distance_to_hard_stop_pct": -0.4028,
        "hard_stop_price": 528.0
      }
    },
    "COIN": {
      "close": 166.02,
      "20d_high": 243.19,
      "20d_low": 139.36,
      "breakout": false,
      "breakdown": false,
      "position": {
        "shares": 13,
        "avg_cost": 262.65,
        "unrealized_pnl_pct": -0.3679,
        "distance_to_hard_stop_pct": -0.3922,
        "hard_stop_price": 231.14
      }
    },
    "CRDO": {
      "close": 124.8,
      "20d_high": 158.87,
      "20d_low": 94.19,
      "breakout": false,
      "breakdown": false,
      "position": {
        "shares": 2,
        "avg_cost": 100,
        "unrealized_pnl_pct": 0.248,
        "distance_to_hard_stop_pct": 0.2949,
        "hard_stop_price": 88.0
      }
    },
    "GOOG": {
      "close": 302.82,
      "20d_high": 350.15,
      "20d_low": 303.9,
      "breakout": false,
      "breakdown": true,
      "position": {
        "shares": 19,
        "avg_cost": 287.7,
        "unrealized_pnl_pct": 0.0526,
        "distance_to_hard_stop_pct": 0.1639,
        "hard_stop_price": 253.18
      }
    },
    "IAU": {
      "close": 91.82,
      "20d_high": 104.4,
      "20d_low": 85.44,
      "breakout": false,
      "breakdown": false,
      "position": {
        "shares": 48,
        "avg_cost": 74.7,
        "unrealized_pnl_pct": 0.2292,
        "distance_to_hard_stop_pct": 0.2841,
        "hard_stop_price": 65.73
      }
    },
    "MCD": {
      "close": 327.62,
      "20d_high": 335.67,
      "20d_low": 302.45,
      "breakout": false,
      "breakdown": false,
      "position": {
        "shares": 22,
        "avg_cost": 300.35,
        "unrealized_pnl_pct": 0.0908,
        "distance_to_hard_stop_pct": 0.1933,
        "hard_stop_price": 264.31
      }
    },
    "META": {
      "close": 639.29,
      "20d_high": 744.0,
      "20d_low": 600.0,
      "breakout": false,
      "breakdown": false,
      "position": {
        "shares": 7,
        "avg_cost": 705.31,
        "unrealized_pnl_pct": -0.0936,
        "distance_to_hard_stop_pct": 0.0291,
        "hard_stop_price": 620.67
      }
    },
    "MU": {
      "close": 399.78,
      "20d_high": 455.5,
      "20d_low": 352.04,
      "breakout": false,
      "breakdown": false,
      "position": {
        "shares": 2,
        "avg_cost": 400,
        "unrealized_pnl_pct": -0.0006,
        "distance_to_hard_stop_pct": 0.1195,
        "hard_stop_price": 352.0
      }
    },
    "NFLX": {
      "close": 77.0,
      "20d_high": 89.9,
      "20d_low": 75.23,
      "breakout": false,
      "breakdown": false,
      "position": {
        "shares": 80,
        "avg_cost": 94.89,
        "unrealized_pnl_pct": -0.1885,
        "distance_to_hard_stop_pct": -0.0845,
        "hard_stop_price": 83.5
      }
    },
    "NVDA": {
      "close": 184.97,
      "20d_high": 194.49,
      "20d_low": 171.03,
      "breakout": false,
      "breakdown": false,
      "position": {
        "shares": 41,
        "avg_cost": 102.17,
        "unrealized_pnl_pct": 0.8104,
        "distance_to_hard_stop_pct": 0.5139,
        "hard_stop_price": 89.91
      }
    },
    "QQQ": {
      "close": 601.3,
      "20d_high": 636.6,
      "20d_low": 594.76,
      "breakout": false,
      "breakdown": false,
      "position": {
        "shares": 6.5,
        "avg_cost": 611.06,
        "unrealized_pnl_pct": -0.016,
        "distance_to_hard_stop_pct": 0.1057,
        "hard_stop_price": 537.74
      }
    },
    "TSLA": {
      "close": 410.63,
      "20d_high": 452.43,
      "20d_low": 387.53,
      "breakout": false,
      "breakdown": false,
      "position": {
        "shares": 11,
        "avg_cost": 266.78,
        "unrealized_pnl_pct": 0.5392,
        "distance_to_hard_stop_pct": 0.4283,
        "hard_stop_price": 234.77
      }
    }
  }
}